{
    "code" : "success",
    "data" :     {
        "endRow" : 8,
        "hasNextPage" : 0,
        "hasPreviousPage" : 0,
        "isFirstPage" : 1,
        "isLastPage" : 1,
        "navigateFirstPage" : 1,
        "navigateLastPage" : 1,
        "navigatePages" : 8,
        "navigatepageNums" : 1,
        "nextPage" : 0,
        "pageNum" : 1,
        "pageSize" : 10,
        "pages" : 1,
        "prePage" : 0,
        "size" : 8,
        "startRow" : 1,
        "total" : 8,
        "list" :         [
            {
                "id": 2731,
                "name": "米莱珠宝 天然摩根石戒指 18K玫瑰金镶嵌钻石戒指 宝石女戒定制",
                "imgUrl": "https://g-search1.alicdn.com/img/bao/uploaded/i4/imgextra/i2/29714427/TB2.X1dnInI8KJjSspeXXcwIpXa_!!0-saturn_solar.jpg_360x360Q90.jpg_.webp",
                "price": "2680.00",
                "carousels": [
                    {
                        "id": 1,
                        "url": "https://img.alicdn.com/imgextra/i1/784477142/TB1yDR5k8cHL1JjSZFBXXaiGXXa_!!0-item_pic.jpg_400x400q90.jpg"
                    },
                    {
                        "id": 2,
                        "url": "https://img.alicdn.com/imgextra/i1/784477142/TB2EYSaeb3XS1JjSZFFXXcvupXa_!!784477142.jpg_400x400q90.jpg"
                    },
                    {
                        "id": 3,
                        "url": "https://img.alicdn.com/imgextra/i2/784477142/TB20IZHkol7MKJjSZFDXXaOEpXa_!!784477142.jpg_400x400q90.jpg"
                    },
                    {
                        "id": 4,
                        "url": "https://img.alicdn.com/imgextra/i4/784477142/TB2kJH8gYsTMeJjy1zcXXXAgXXa_!!784477142.jpg_400x400q90.jpg"
                    },
                    {
                        "id": 5,
                        "url": "https://img.alicdn.com/imgextra/i3/784477142/TB25Y73pRcHL1JjSZJiXXcKcpXa_!!784477142.jpg_400x400q90.jpg"
                    }
                ],
                "details": [
                    {
                        "id": 1,
                        "url": "https://img.alicdn.com/imgextra/i1/784477142/TB2jIkRdjihSKJjy0FlXXadEXXa_!!784477142.jpg"
                    },
                    {
                        "id": 2,
                        "url": "https://img.alicdn.com/imgextra/i4/784477142/O1CN01oP6Hb622d5BaCopWG_!!784477142.jpg"
                    },
                    {
                        "id": 3,
                        "url": "https://img.alicdn.com/imgextra/i4/784477142/TB2BMB8lEUIL1JjSZFrXXb3xFXa_!!784477142.jpg"
                    },
                    {
                        "id": 4,
                        "url": "https://img.alicdn.com/imgextra/i3/784477142/TB2.MpEgvNNTKJjSspeXXaSwpXa_!!784477142.jpg"
                    },
                    {
                        "id": 5,
                        "url": "https://img.alicdn.com/imgextra/i3/784477142/TB2AlFXlgMPMeJjy1XdXXasrXXa_!!784477142.jpg"
                    },
                    {
                        "id": 6,
                        "url": "https://img.alicdn.com/imgextra/i2/784477142/TB2f4x0lzoIL1JjSZFyXXbFBpXa_!!784477142.jpg"
                    },
                    {
                        "id": 7,
                        "url": "https://img.alicdn.com/imgextra/i2/784477142/TB2QssJdaagSKJjy0FhXXcrbFXa_!!784477142.jpg"
                    },
                    {
                        "id": 8,
                        "url": "https://img.alicdn.com/imgextra/i2/784477142/TB22mc.kUF7MKJjSZFLXXcMBVXa_!!784477142.jpg"
                    },
                    {
                        "id": 9,
                        "url": "https://img.alicdn.com/imgextra/i1/784477142/TB2JHN1cLBNTKJjy1zdXXaScpXa_!!784477142.jpg"
                    },
                    {
                        "id": 10,
                        "url": "https://img.alicdn.com/imgextra/i3/784477142/TB2U1lPcLBNTKJjSszcXXbO2VXa_!!784477142.jpg"
                    },
                    {
                        "id": 11,
                        "url": "https://img.alicdn.com/imgextra/i2/784477142/TB2ygmXlBcHL1JjSZFBXXaiGXXa_!!784477142.jpg"
                    },
                    {
                        "id": 12,
                        "url": "https://img.alicdn.com/imgextra/i3/784477142/TB2AJoJdaagSKJjy0FhXXcrbFXa_!!784477142.jpg"
                    },
                    {
                        "id": 13,
                        "url": "https://img.alicdn.com/imgextra/i2/784477142/TB2YeQUdaagSKJjy0FcXXcZeVXa_!!784477142.jpg"
                    }
                ]
            },
            {
                "id": 2732,
                "name": "米莱珠宝 18K金链子素链 项链女款 锁骨链18K玫瑰金配链百搭O",
                "imgUrl": "https://g-search3.alicdn.com/img/bao/uploaded/i4/i1/784477142/TB10DEkar1YBuNjSszhXXcUsFXa_!!0-item_pic.jpg_360x360Q90.jpg_.webp",
                "price": "573.00",
                "carousels": [
                    {
                        "id": 1,
                        "url": "https://img.alicdn.com/imgextra/i1/784477142/TB10DEkar1YBuNjSszhXXcUsFXa_!!0-item_pic.jpg_400x400q90.jpg"
                    },
                    {
                        "id": 2,
                        "url": "https://img.alicdn.com/imgextra/i2/784477142/TB2Td_ujl0lpuFjSszdXXcdxFXa_!!784477142.jpg_400x400q90.jpg"
                    },
                    {
                        "id": 3,
                        "url": "https://img.alicdn.com/imgextra/i2/784477142/TB2VaPPjgFkpuFjSspnXXb4qFXa_!!784477142.jpg_400x400q90.jpg"
                    },
                    {
                        "id": 4,
                        "url": "https://img.alicdn.com/imgextra/i2/784477142/TB2Mr_OjbplpuFjSspiXXcdfFXa_!!784477142.jpg_400x400q90.jpg"
                    },
                    {
                        "id": 5,
                        "url": "https://img.alicdn.com/imgextra/i4/784477142/TB2klLQkYxmpuFjSZJiXXXauVXa_!!784477142.jpg_400x400q90.jpg"
                    }
                ],
                "details": [
                    {
                        "id": 1,
                        "url": "https://img.alicdn.com/imgextra/i3/784477142/TB2tLPTk98mpuFjSZFMXXaxpVXa_!!784477142.jpg"
                    },
                    {
                        "id": 2,
                        "url": "https://img.alicdn.com/imgextra/i4/784477142/TB29ytKlr5YBuNjSspoXXbeNFXa_!!784477142.jpg"
                    },
                    {
                        "id": 3,
                        "url": "https://img.alicdn.com/imgextra/i1/784477142/TB2avTTk98mpuFjSZFMXXaxpVXa_!!784477142.jpg"
                    },
                    {
                        "id": 4,
                        "url": "https://img.alicdn.com/imgextra/i3/784477142/TB2JeFvbzJTMKJjSZFPXXbHUFXa_!!784477142.jpg"
                    },
                    {
                        "id": 5,
                        "url": "https://img.alicdn.com/imgextra/i1/784477142/TB2_mG7k0BopuFjSZPcXXc9EpXa_!!784477142.jpg"
                    },
                    {
                        "id": 6,
                        "url": "https://img.alicdn.com/imgextra/i2/784477142/TB2tNsffyC9MuFjSZFoXXbUzFXa_!!784477142.jpg"
                    },
                    {
                        "id": 7,
                        "url": "https://img.alicdn.com/imgextra/i2/784477142/TB2eCbGk4xmpuFjSZFNXXXrRXXa_!!784477142.jpg"
                    },
                    {
                        "id": 8,
                        "url": "https://img.alicdn.com/imgextra/i1/784477142/TB2X7G_k4tmpuFjSZFqXXbHFpXa_!!784477142.jpg"
                    },
                    {
                        "id": 9,
                        "url": "https://img.alicdn.com/imgextra/i2/784477142/TB25czJjbtlpuFjSspoXXbcDpXa_!!784477142.jpg"
                    },
                    {
                        "id": 10,
                        "url": "https://img.alicdn.com/imgextra/i2/784477142/TB2kMbujbtlpuFjSspfXXXLUpXa_!!784477142.jpg"
                    },
                    {
                        "id": 11,
                        "url": "https://img.alicdn.com/imgextra/i2/784477142/TB2npQUbr_0UKFjy1XaXXbKfXXa_!!784477142.jpg"
                    },
                    {
                        "id": 12,
                        "url": "https://img.alicdn.com/imgextra/i1/784477142/TB2F3_DjmxjpuFjSszeXXaeMVXa_!!784477142.jpg"
                    }
                ]
            },
            {
                "id": 2733,
                "name": "米莱珠宝 4.5克拉天然摩根石戒指 女 18K玫瑰金钻石戒指 钻戒女戒",
                "imgUrl": "https://g-search1.alicdn.com/img/bao/uploaded/i4/i1/784477142/TB1RhxnSVXXXXaVXVXXXXXXXXXX_!!0-item_pic.jpg_360x360Q90.jpg_.webp",
                "price": "2929.00",
                "carousels": [
                    {
                        "id": 1,
                        "url": "https://img.alicdn.com/imgextra/i1/784477142/TB1RhxnSVXXXXaVXVXXXXXXXXXX_!!0-item_pic.jpg_400x400q90.jpg"
                    },
                    {
                        "id": 2,
                        "url": "https://img.alicdn.com/imgextra/i3/784477142/TB2B1hNgVXXXXXIXXXXXXXXXXXX_!!784477142.jpg_400x400q90.jpg"
                    },
                    {
                        "id": 3,
                        "url": "https://img.alicdn.com/imgextra/i1/784477142/TB2IOxIgVXXXXaCXXXXXXXXXXXX_!!784477142.jpg_400x400q90.jpg"
                    },
                    {
                        "id": 4,
                        "url": "https://img.alicdn.com/imgextra/i2/784477142/TB2hqhlgVXXXXabXpXXXXXXXXXX_!!784477142.jpg_400x400q90.jpg"
                    },
                    {
                        "id": 5,
                        "url": "https://img.alicdn.com/imgextra/i2/784477142/TB26atzgVXXXXcuXXXXXXXXXXXX_!!784477142.jpg_400x400q90.jpg"
                    }
                ],
                "details": [
                    {
                        "id": 1,
                        "url": "https://img.alicdn.com/imgextra/i3/784477142/O1CN01G8UH4522d5BcFqrkS_!!784477142.jpg"
                    },
                    {
                        "id": 2,
                        "url": "https://img.alicdn.com/imgextra/i3/784477142/TB2ZwZmcsv_F1JjSZFGXXa8.FXa_!!784477142.jpg"
                    },
                    {
                        "id": 3,
                        "url": "https://img.alicdn.com/imgextra/i1/784477142/TB2kpv0cwAEF1JjSZFLXXbzNXXa_!!784477142.jpg"
                    },
                    {
                        "id": 4,
                        "url": "https://img.alicdn.com/imgextra/i1/784477142/TB2ClYPX8TCIuJjSZPiXXb5vVXa_!!784477142.jpg"
                    },
                    {
                        "id": 5,
                        "url": "https://img.alicdn.com/imgextra/i1/784477142/TB2zl_RX8PCIuJjSZJiXXaCVXXa_!!784477142.jpg"
                    },
                    {
                        "id": 6,
                        "url": "https://img.alicdn.com/imgextra/i3/23304479/TB25K8hgVXXXXc6XXXXXXXXXXXX_!!23304479.jpg"
                    },
                    {
                        "id": 7,
                        "url": "https://img.alicdn.com/imgextra/i1/23304479/TB2dIlrgVXXXXbbXXXXXXXXXXXX_!!23304479.jpg"
                    },
                    {
                        "id": 8,
                        "url": "https://img.alicdn.com/imgextra/i4/23304479/TB2qm35gFXXXXbQXpXXXXXXXXXX_!!23304479.jpg"
                    },
                    {
                        "id": 9,
                        "url": "https://img.alicdn.com/imgextra/i2/23304479/TB2RJBXgVXXXXa8XpXXXXXXXXXX_!!23304479.jpg"
                    },
                    {
                        "id": 10,
                        "url": "https://img.alicdn.com/imgextra/i2/23304479/TB2GMlfgVXXXXXHXpXXXXXXXXXX_!!23304479.jpg"
                    },
                    {
                        "id": 11,
                        "url": "https://img.alicdn.com/imgextra/i2/23304479/TB2jY77gFXXXXbzXpXXXXXXXXXX_!!23304479.jpg"
                    },
                    {
                        "id": 12,
                        "url": "https://img.alicdn.com/imgextra/i4/23304479/TB2dGIOXVXXXXcSXXXXXXXXXXXX_!!23304479.jpg"
                    },
                    {
                        "id": 13,
                        "url": "https://img.alicdn.com/imgextra/i2/23304479/TB2UUdmgVXXXXbIXXXXXXXXXXXX_!!23304479.jpg"
                    },
                    {
                        "id": 14,
                        "url": "https://img.alicdn.com/imgextra/i3/23304479/TB2_TXAgVXXXXXgXXXXXXXXXXXX_!!23304479.jpg"
                    },
                    {
                        "id": 15,
                        "url": "https://img.alicdn.com/imgextra/i4/23304479/TB2QHNfgVXXXXXHXpXXXXXXXXXX_!!23304479.jpg"
                    }
                ]
            },
            {
                "id": 2734,
                "name": "米莱珠宝 花冕皇冠 天然红宝石戒指女 18K金宝石戒指 镶嵌加工",
                "imgUrl": "https://g-search2.alicdn.com/img/bao/uploaded/i4/i3/TB1_wAZPFXXXXbtXFXXXXXXXXXX_!!0-item_pic.jpg_360x360Q90.jpg_.webp",
                "price": "3090.00",
                "carousels": [
                    {
                        "id": 1,
                        "url": "https://img.alicdn.com/imgextra/i3/TB1_wAZPFXXXXbtXFXXXXXXXXXX_!!0-item_pic.jpg_400x400q90.jpg"
                    },
                    {
                        "id": 2,
                        "url": "https://img.alicdn.com/imgextra/i3/784477142/TB27PA9fHVkpuFjSspcXXbSMVXa_!!784477142.jpg_400x400q90.jpg"
                    },
                    {
                        "id": 3,
                        "url": "https://img.alicdn.com/imgextra/i1/784477142/TB2tykcg4hmpuFjSZFyXXcLdFXa_!!784477142.jpg_400x400q90.jpg"
                    },
                    {
                        "id": 4,
                        "url": "https://img.alicdn.com/imgextra/i2/784477142/O1CN01nWMvLu22d5DlNAgFF_!!784477142.jpg_400x400q90.jpg"
                    },
                    {
                        "id": 5,
                        "url": "https://img.alicdn.com/imgextra/i1/784477142/TB26YAUfR0lpuFjSszdXXcdxFXa_!!784477142.jpg_400x400q90.jpg"
                    }
                ],
                "details": [
                    {
                        "id": 1,
                        "url": "https://img.alicdn.com/imgextra/i1/784477142/TB2KOyIX7onyKJjSZFtXXXNaVXa_!!784477142.jpg"
                    },
                    {
                        "id": 2,
                        "url": "https://img.alicdn.com/imgextra/i2/784477142/TB2t_HXggxlpuFjy0FoXXa.lXXa_!!784477142.jpg"
                    },
                    {
                        "id": 3,
                        "url": "https://img.alicdn.com/imgextra/i4/784477142/TB2HzOghxtmpuFjSZFqXXbHFpXa_!!784477142.jpg"
                    },
                    {
                        "id": 4,
                        "url": "https://img.alicdn.com/imgextra/i2/784477142/TB23ACngmBjpuFjSsplXXa5MVXa_!!784477142.jpg"
                    },
                    {
                        "id": 5,
                        "url": "https://img.alicdn.com/imgextra/i1/784477142/TB2hgm1hxlmpuFjSZPfXXc9iXXa_!!784477142.jpg"
                    },
                    {
                        "id": 6,
                        "url": "https://img.alicdn.com/imgextra/i1/784477142/TB2T2mYhrBmpuFjSZFAXXaQ0pXa_!!784477142.jpg"
                    },
                    {
                        "id": 7,
                        "url": "https://img.alicdn.com/imgextra/i2/784477142/TB2LDqKhxxmpuFjSZFNXXXrRXXa_!!784477142.jpg"
                    },
                    {
                        "id": 8,
                        "url": "https://img.alicdn.com/imgextra/i2/784477142/TB2R85QhC8mpuFjSZFMXXaxpVXa_!!784477142.jpg"
                    },
                    {
                        "id": 9,
                        "url": "https://img.alicdn.com/imgextra/i1/784477142/TB2KrmLhtRopuFjSZFtXXcanpXa_!!784477142.jpg"
                    }
                ]
            },
            {
                "id": 2735,
                "name": "米莱珠宝 天然粉红碧水晶橄榄石托帕石吊坠女 18K金钻石定制项链",
                "imgUrl": "https://g-search2.alicdn.com/img/bao/uploaded/i4/i4/TB16uwzSpXXXXauaXXXXXXXXXXX_!!0-item_pic.jpg_360x360Q90.jpg_.webp",
                "price": "2930.00",
                "carousels": [
                    {
                        "id": 1,
                        "url": "https://img.alicdn.com/imgextra/i4/TB16uwzSpXXXXauaXXXXXXXXXXX_!!0-item_pic.jpg_400x400q90.jpg"
                    },
                    {
                        "id": 2,
                        "url": "https://img.alicdn.com/imgextra/i4/TB1nUwtHXXXXXaiXFXXXXXXXXXX_!!0-item_pic.jpg_400x400q90.jpg"
                    },
                    {
                        "id": 3,
                        "url": "https://img.alicdn.com/imgextra/i3/784477142/TB2owgEyrxmpuFjSZJiXXXauVXa_!!784477142.jpg_400x400q90.jpg"
                    },
                    {
                        "id": 4,
                        "url": "https://img.alicdn.com/imgextra/i3/784477142/O1CN01TSOVUs22d5DxV0H6i_!!784477142.jpg_400x400q90.jpg"
                    },
                    {
                        "id": 5,
                        "url": "https://img.alicdn.com/imgextra/i3/784477142/O1CN01105o0z22d5DwKWUJr_!!784477142.jpg_400x400q90.jpg"
                    }
                ],
                "details": [
                    {
                        "id": 1,
                        "url": "https://img.alicdn.com/imgextra/i2/784477142/TB25QeXcXXXXXa0XXXXXXXXXXXX_!!784477142.jpg"
                    },
                    {
                        "id": 2,
                        "url": "https://img.alicdn.com/imgextra/i2/784477142/TB27FXQbVXXXXcbXpXXXXXXXXXX_!!784477142.jpg"
                    },
                    {
                        "id": 3,
                        "url": "https://img.alicdn.com/imgextra/i4/784477142/TB26CVUbVXXXXcAXXXXXXXXXXXX_!!784477142.jpg"
                    },
                    {
                        "id": 4,
                        "url": "https://img.alicdn.com/imgextra/i4/784477142/TB2DN4RbVXXXXabXpXXXXXXXXXX_!!784477142.jpg"
                    },
                    {
                        "id": 5,
                        "url": "https://img.alicdn.com/imgextra/i2/784477142/TB2pOX.cXXXXXbxXXXXXXXXXXXX_!!784477142.jpg"
                    },
                    {
                        "id": 6,
                        "url": "https://img.alicdn.com/imgextra/i1/784477142/TB2zaibcXXXXXXRXXXXXXXXXXXX_!!784477142.jpg"
                    },
                    {
                        "id": 7,
                        "url": "https://img.alicdn.com/imgextra/i4/784477142/TB2Pst.cXXXXXbUXXXXXXXXXXXX_!!784477142.jpg"
                    },
                    {
                        "id": 8,
                        "url": "https://img.alicdn.com/imgextra/i2/784477142/TB2_k48cXXXXXXoXpXXXXXXXXXX_!!784477142.jpg"
                    },
                    {
                        "id": 9,
                        "url": "https://img.alicdn.com/imgextra/i2/784477142/TB2y7VSbVXXXXc6XXXXXXXXXXXX_!!784477142.jpg"
                    },
                    {
                        "id": 10,
                        "url": "https://img.alicdn.com/imgextra/i1/784477142/TB22NXVbVXXXXb7XXXXXXXXXXXX_!!784477142.jpg"
                    },
                    {
                        "id": 11,
                        "url": "https://img.alicdn.com/imgextra/i3/784477142/TB2fZBWbVXXXXb8XXXXXXXXXXXX_!!784477142.jpg"
                    },
                    {
                        "id": 12,
                        "url": "https://img.alicdn.com/imgextra/i3/784477142/TB2L7hWbVXXXXcfXXXXXXXXXXXX_!!784477142.jpg"
                    },
                    {
                        "id": 13,
                        "url": "https://img.alicdn.com/imgextra/i1/784477142/TB2QhXYbVXXXXbMXXXXXXXXXXXX_!!784477142.jpg"
                    },
                    {
                        "id": 14,
                        "url": "https://img.alicdn.com/imgextra/i3/784477142/TB2FDhRbVXXXXXzXpXXXXXXXXXX_!!784477142.jpg"
                    },
                    {
                        "id": 15,
                        "url": "https://img.alicdn.com/imgextra/i1/784477142/TB2CvtRbVXXXXX5XpXXXXXXXXXX_!!784477142.jpg"
                    },
                    {
                        "id": 16,
                        "url": "https://img.alicdn.com/imgextra/i3/784477142/TB2h8dRbVXXXXX1XpXXXXXXXXXX_!!784477142.jpg"
                    },
                    {
                        "id": 17,
                        "url": "https://img.alicdn.com/imgextra/i1/784477142/TB2VoaXcXXXXXXMXXXXXXXXXXXX_!!784477142.jpg"
                    },
                    {
                        "id": 18,
                        "url": "https://img.alicdn.com/imgextra/i2/784477142/TB23uF8cXXXXXXwXpXXXXXXXXXX_!!784477142.jpg"
                    },
                    {
                        "id": 19,
                        "url": "https://img.alicdn.com/imgextra/i4/784477142/TB2pZh_cXXXXXcqXXXXXXXXXXXX_!!784477142.jpg"
                    },
                    {
                        "id": 20,
                        "url": "https://img.alicdn.com/imgextra/i1/784477142/TB23p9XcXXXXXbcXXXXXXXXXXXX_!!784477142.jpg"
                    },
                    {
                        "id": 21,
                        "url": "https://img.alicdn.com/imgextra/i1/784477142/TB2ZCl9cXXXXXcKXXXXXXXXXXXX_!!784477142.jpg"
                    },
                    {
                        "id": 22,
                        "url": "https://img.alicdn.com/imgextra/i1/784477142/TB2ZEaXcXXXXXaqXXXXXXXXXXXX_!!784477142.jpg"
                    }
                ]
            },
            {
                "id": 2736,
                "name": "米莱珠宝 天然海蓝宝项链女 18K金镶嵌钻石吊坠 宝石加工定制",
                "imgUrl": "https://g-search3.alicdn.com/img/bao/uploaded/i4/i2/784477142/O1CN0199pSjq22d5Dl8C7HK_!!0-item_pic.jpg_360x360Q90.jpg_.webp",
                "price": "5879.00",
                "carousels": [
                    {
                        "id": 1,
                        "url": "https://img.alicdn.com/imgextra/i2/784477142/O1CN0199pSjq22d5Dl8C7HK_!!0-item_pic.jpg_400x400q90.jpg"
                    },
                    {
                        "id": 2,
                        "url": "https://img.alicdn.com/imgextra/i3/784477142/O1CN013yAiUA22d5DnyJDdo_!!784477142.jpg_400x400q90.jpg"
                    },
                    {
                        "id": 3,
                        "url": "https://img.alicdn.com/imgextra/i2/784477142/O1CN01SajGC522d5Dmbm5T5_!!784477142.jpg_400x400q90.jpg"
                    },
                    {
                        "id": 4,
                        "url": "https://img.alicdn.com/imgextra/i3/784477142/O1CN017tv4os22d5DmjgqgA_!!784477142.jpg_400x400q90.jpg"
                    },
                    {
                        "id": 5,
                        "url": "https://img.alicdn.com/imgextra/i1/784477142/O1CN01jtNg3n22d5Dmjg6vH_!!784477142.jpg_400x400q90.jpg"
                    }
                ],
                "details": [
                    {
                        "id": 1,
                        "url": "https://img.alicdn.com/imgextra/i1/784477142/O1CN01s7JGK322d5DpZHosy_!!784477142.png"
                    },
                    {
                        "id": 2,
                        "url": "https://img.alicdn.com/imgextra/i1/784477142/O1CN01s7HQ1P22d5DlloQI1_!!784477142.jpg"
                    },
                    {
                        "id": 3,
                        "url": "https://img.alicdn.com/imgextra/i4/784477142/O1CN01Y13gY322d5Debrqwf_!!784477142.jpg"
                    },
                    {
                        "id": 4,
                        "url": "https://img.alicdn.com/imgextra/i2/784477142/O1CN01Bj7efG22d5DmoTRV1_!!784477142.jpg"
                    },
                    {
                        "id": 5,
                        "url": "https://img.alicdn.com/imgextra/i3/784477142/O1CN01F9ACYn22d5DoaH5k0_!!784477142.jpg"
                    },
                    {
                        "id": 6,
                        "url": "https://img.alicdn.com/imgextra/i2/784477142/TB2g5cTpVXXXXb7XXXXXXXXXXXX_!!784477142.jpg"
                    },
                    {
                        "id": 7,
                        "url": "https://img.alicdn.com/imgextra/i4/784477142/TB2aTgwpVXXXXX4XFXXXXXXXXXX_!!784477142.jpg"
                    },
                    {
                        "id": 8,
                        "url": "https://img.alicdn.com/imgextra/i1/784477142/O1CN01Vsqd5u22d5Do6jHvJ_!!784477142.jpg"
                    }
                ]
            },
            {
                "id": 2737,
                "name": "米莱珠宝 精致唯美 天然鸽血红红宝石戒指 18K金镶嵌钻石女戒定制",
                "imgUrl": "https://g-search2.alicdn.com/img/bao/uploaded/i4/i3/784477142/O1CN01DtdVHv22d5E3PnsjZ_!!0-item_pic.jpg_360x360Q90.jpg_.webp",
                "price": "1980.00",
                "carousels": [
                    {
                        "id": 1,
                        "url": "https://img.alicdn.com/imgextra/i3/784477142/O1CN01DtdVHv22d5E3PnsjZ_!!0-item_pic.jpg_400x400q90.jpg"
                    },
                    {
                        "id": 2,
                        "url": "https://img.alicdn.com/imgextra/i3/784477142/O1CN01ptxBq422d5E7ERs6M_!!784477142.jpg_400x400q90.jpg"
                    },
                    {
                        "id": 3,
                        "url": "https://img.alicdn.com/imgextra/i1/784477142/O1CN01AVoPYj22d5E7ERP24_!!784477142.jpg_400x400q90.jpg"
                    },
                    {
                        "id": 4,
                        "url": "https://img.alicdn.com/imgextra/i1/784477142/O1CN01W4P5lm22d5E4uPDW0_!!784477142.jpg_400x400q90.jpg"
                    },
                    {
                        "id": 5,
                        "url": "https://img.alicdn.com/imgextra/i2/784477142/O1CN014h6xi322d5E33BRVe_!!784477142.jpg_400x400q90.jpg"
                    }
                ],
                "details": [
                    {
                        "id": 1,
                        "url": "https://img.alicdn.com/imgextra/i2/784477142/O1CN01CkIBpJ22d5E2ECgdn_!!784477142.jpg"
                    },
                    {
                        "id": 2,
                        "url": "https://img.alicdn.com/imgextra/i3/784477142/O1CN01oOgvvw22d5E3W16LH_!!784477142.jpg"
                    },
                    {
                        "id": 3,
                        "url": "https://img.alicdn.com/imgextra/i2/784477142/O1CN014h6xi322d5E33BRVe_!!784477142.jpg"
                    },
                    {
                        "id": 4,
                        "url": "https://img.alicdn.com/imgextra/i1/784477142/O1CN01W4P5lm22d5E4uPDW0_!!784477142.jpg"
                    },
                    {
                        "id": 5,
                        "url": "https://img.alicdn.com/imgextra/i1/784477142/O1CN01iPAVZ622d5E4uMXDE_!!784477142.jpg"
                    },
                    {
                        "id": 6,
                        "url": "https://img.alicdn.com/imgextra/i3/784477142/O1CN01QB91YA22d5E7QuWn6_!!784477142.jpg"
                    },
                    {
                        "id": 7,
                        "url": "https://img.alicdn.com/imgextra/i3/784477142/O1CN01ptxBq422d5E7ERs6M_!!784477142.jpg"
                    },
                    {
                        "id": 8,
                        "url": "https://img.alicdn.com/imgextra/i1/784477142/O1CN01AVoPYj22d5E7ERP24_!!784477142.jpg"
                    },
                    {
                        "id": 9,
                        "url": "https://img.alicdn.com/imgextra/i1/784477142/O1CN01ReIe9s22d5Dxhyhyv_!!784477142.jpg"
                    },
                    {
                        "id": 10,
                        "url": "https://img.alicdn.com/imgextra/i4/784477142/O1CN01D5hKak22d5E4uMjjv_!!784477142.jpg"
                    }
                ]
            },
            {
                "id": 2738,
                "name": "米莱珠宝 0.75克拉天然祖母绿戒指 18K金宝石排戒 情侣戒指男女款",
                "imgUrl": "https://g-search1.alicdn.com/img/bao/uploaded/i4/i3/784477142/TB1Vqy9SFXXXXcmaXXXXXXXXXXX_!!0-item_pic.jpg_360x360Q90.jpg_.webp",
                "price": "3280.00",
                "carousels": [
                    {
                        "id": 1,
                        "url": "https://img.alicdn.com/imgextra/i3/784477142/TB1Vqy9SFXXXXcmaXXXXXXXXXXX_!!0-item_pic.jpg_400x400q90.jpg"
                    },
                    {
                        "id": 2,
                        "url": "https://img.alicdn.com/imgextra/i1/784477142/TB2j1thd3IlyKJjSZFqXXX9xpXa_!!784477142.jpg_400x400q90.jpg"
                    },
                    {
                        "id": 3,
                        "url": "https://img.alicdn.com/imgextra/i2/784477142/TB25ldIfhaK.eBjSZFwXXXjsFXa_!!784477142.jpg_400x400q90.jpg"
                    },
                    {
                        "id": 4,
                        "url": "https://img.alicdn.com/imgextra/i4/784477142/TB2j5UYd_CWBKNjSZFtXXaC3FXa_!!784477142.jpg_400x400q90.jpg"
                    },
                    {
                        "id": 5,
                        "url": "https://img.alicdn.com/imgextra/i3/784477142/TB2dvJjsMFkpuFjSspnXXb4qFXa_!!784477142.png_400x400q90.jpg"
                    }
                ],
                "details": [
                    {
                        "id": 1,
                        "url": "https://img.alicdn.com/imgextra/i4/784477142/T2iuKZXqhXXXXXXXXX_!!784477142.png"
                    },
                    {
                        "id": 2,
                        "url": "https://img.alicdn.com/imgextra/i3/784477142/O1CN0122d5ANwtCz7d70M_!!784477142.jpg"
                    },
                    {
                        "id": 3,
                        "url": "https://img.alicdn.com/imgextra/i4/784477142/TB26xOLbpXXXXayXXXXXXXXXXXX_!!784477142.jpg"
                    },
                    {
                        "id": 4,
                        "url": "https://img.alicdn.com/imgextra/i1/784477142/TB2GnXVaXXXXXcwXXXXXXXXXXXX_!!784477142.jpg"
                    },
                    {
                        "id": 5,
                        "url": "https://img.alicdn.com/imgextra/i3/784477142/TB2YcdVaXXXXXcQXXXXXXXXXXXX_!!784477142.jpg"
                    },
                    {
                        "id": 6,
                        "url": "https://img.alicdn.com/imgextra/i4/784477142/TB2e4XYaXXXXXXNXpXXXXXXXXXX_!!784477142.jpg"
                    },
                    {
                        "id": 7,
                        "url": "https://img.alicdn.com/imgextra/i4/784477142/TB27bh3aXXXXXXLXXXXXXXXXXXX_!!784477142.jpg"
                    },
                    {
                        "id": 8,
                        "url": "https://img.alicdn.com/imgextra/i3/784477142/TB2ql4VaXXXXXXfXpXXXXXXXXXX_!!784477142.jpg"
                    },
                    {
                        "id": 9,
                        "url": "https://img.alicdn.com/imgextra/i1/784477142/TB2kyhYaXXXXXXqXpXXXXXXXXXX_!!784477142.jpg"
                    },
                    {
                        "id": 10,
                        "url": "https://img.alicdn.com/imgextra/i4/784477142/TB2dBRVaXXXXXcWXXXXXXXXXXXX_!!784477142.jpg"
                    }
                ]
            },
            {
                "id": 2739,
                "name": "米莱珠宝 红宝石戒指天然鸽血吊坠手链耳钉现货 彩色宝石定制专用",
                "imgUrl": "https://g-search3.alicdn.com/img/bao/uploaded/i4/i1/23304479/TB24yTfGASWBuNjSszdXXbeSpXa_!!23304479.jpg_360x360Q90.jpg_.webp",
                "price": "1800.00",
                "carousels": [
                    {
                        "id": 1,
                        "url": "https://gd4.alicdn.com/imgextra/i1/23304479/TB24yTfGASWBuNjSszdXXbeSpXa_!!23304479.jpg_400x400.jpg_.webp"
                    },
                    {
                        "id": 2,
                        "url": "https://gd4.alicdn.com/imgextra/i4/23304479/T2eyxNXYpXXXXXXXXX_!!23304479.jpg_400x400.jpg_.webp"
                    }
                ],
                "details": [
                    {
                        "id": 1,
                        "url": "https://img.alicdn.com/imgextra/i4/23304479/TB28hjfE9tYBeNjSspkXXbU8VXa_!!23304479.jpg"
                    },
                    {
                        "id": 2,
                        "url": "https://img.alicdn.com/imgextra/i4/23304479/TB2e.VDE29TBuNjy1zbXXXpepXa_!!23304479.jpg"
                    },
                    {
                        "id": 3,
                        "url": "https://img.alicdn.com/imgextra/i1/23304479/TB2nDzfE21TBuNjy0FjXXajyXXa_!!23304479.jpg"
                    }
                ]
            },
            {
                "id": 2740,
                "name": "米莱珠宝 现货J64-J88 天然摩根石戒指女 18K金彩色宝石耳钉耳环",
                "imgUrl": "https://g-search1.alicdn.com/img/bao/uploaded/i4/i1/23304479/O1CN01AgjJIB1ixQZ3gIYI0_!!23304479.jpg_360x360Q90.jpg_.webp",
                "price": "800.00",
                "carousels": [
                    {
                        "id": 1,
                        "url": "https://gd1.alicdn.com/imgextra/i1/23304479/O1CN01AgjJIB1ixQZ3gIYI0_!!23304479.jpg_400x400.jpg_.webp"
                    }
                ],
                "details": [
                    {
                        "id": 1,
                        "url": "https://img.alicdn.com/imgextra/i1/23304479/O1CN01AgjJIB1ixQZ3gIYI0_!!23304479.jpg"
                    },
                    {
                        "id": 2,
                        "url": "https://img.alicdn.com/imgextra/i3/23304479/O1CN01anUhnR1ixQZ4ZO7oi_!!23304479.png"
                    }
                ]
            }
        ]
    }
}
